mfn_sdk/__init__.py
mfn_sdk/deprecated.py
mfn_sdk/function.py
mfn_sdk/mfnclient.py
mfn_sdk/storage.py
mfn_sdk/trigger.py
mfn_sdk/workflow.py
mfn_sdk-0.8.9.dist-info/LICENSE
mfn_sdk-0.8.9.dist-info/METADATA
mfn_sdk-0.8.9.dist-info/WHEEL
mfn_sdk-0.8.9.dist-info/top_level.txt
mfn_sdk-0.8.9.dist-info/RECORD
