Metadata-Version: 2.1
Name: mfn-sdk
Version: 0.8.9
Summary: MicroFunctions Client SDK
Home-page: https://github.com/knix-microfunctions/knix
Author: The KNIX authors
Author-email: knix-dev@list.nokia.com
License: Apache-2.0
Platform: UNKNOWN
Classifier: Programming Language :: Python :: 3
Classifier: Operating System :: OS Independent
Requires-Python: >=3.6
Requires-Dist: requests
Requires-Dist: urllib3
